lacss/__init__.py
lacss/data/__init__.py
lacss/data/augment.py
lacss/data/augment_.py
lacss/data/generator.py
lacss/data/utils.py
lacss/deploy/__init__.py
lacss/deploy/cellpose_server.py
lacss/deploy/common.py
lacss/deploy/predict.py
lacss/deploy/remote_server.py
lacss/deploy/segformer_server.py
lacss/losses/__init__.py
lacss/losses/auxiliary.py
lacss/losses/common.py
lacss/losses/instance.py
lacss/metrics/__init__.py
lacss/metrics/common.py
lacss/metrics/dice.py
lacss/metrics/ranked.py
lacss/modules/__init__.py
lacss/modules/backbone.py
lacss/modules/common.py
lacss/modules/convnext.py
lacss/modules/integrators.py
lacss/modules/lacss.py
lacss/modules/lpn.py
lacss/modules/lpn3d.py
lacss/modules/resnet.py
lacss/modules/segmentor.py
lacss/modules/segmentor3d.py
lacss/modules/unet.py
lacss/modules/video_integrator.py
lacss/modules/vit.py
lacss/ops/__init__.py
lacss/ops/boxes.py
lacss/ops/image.py
lacss/ops/nms.py
lacss/ops/patches.py
lacss/ops/uda.py
lacss/tracking/__init__.py
lacss/tracking/kalman.py
lacss/tracking/seqnms.py
lacss/tracking/utils.py
lacss/tracking/ztracker.py
lacss/train/__init__.py
lacss/train/adversal_uda.py
lacss/train/cks.py
lacss/train/lacss_trainer.py
lacss/train/mean_teacher.py
lacss/train/train.py
lacss/train/video.py
lacss/typing.py
lacss/utils.py
lacss-0.15.2.dist-info/LICENSE
lacss-0.15.2.dist-info/METADATA
lacss-0.15.2.dist-info/WHEEL
lacss-0.15.2.dist-info/RECORD
