Metadata-Version: 2.3
Name: lacss
Version: 0.15.2
Summary: Tools for cell segmentation
License: MIT
Author: Ji Yu
Author-email: jyu@uchc.edu
Requires-Python: >=3.10,<4.0
Classifier: License :: OSI Approved :: MIT License
Classifier: Programming Language :: Python :: 3
Classifier: Programming Language :: Python :: 3.10
Classifier: Programming Language :: Python :: 3.11
Classifier: Programming Language :: Python :: 3.12
Classifier: Programming Language :: Python :: 3.13
Provides-Extra: cuda12
Provides-Extra: train
Requires-Dist: biopb (>=0.1.2,<0.2.0)
Requires-Dist: flax (>=0.10,<0.11)
Requires-Dist: grpcio (>=1.66,<2.0)
Requires-Dist: imagecodecs (>=2023.3.16,<2024.0.0)
Requires-Dist: imageio (>=2.9.0,<3.0.0)
Requires-Dist: jax[cuda12] (>=0.4,<0.5)
Requires-Dist: ml-collections (>=0.1.1,<0.2.0) ; extra == "train"
Requires-Dist: numpy (<2.0)
Requires-Dist: opencv-python-headless (>=4,<5)
Requires-Dist: scikit-image (>=0.19.0)
Requires-Dist: tensorflow (>=2.16.1,<3.0.0) ; extra == "train"
Requires-Dist: tqdm (>=4.65.0,<5.0.0)
Requires-Dist: typer (>=0.12.3,<0.13.0)
Requires-Dist: vedo (>=2025.5.3,<2026.0.0)
Requires-Dist: xtrain (>=0.4,<0.5) ; extra == "train"
